MANIFEST.in
README.md
changelog.py
setup.py
easy_getch/__init__.py
easy_getch/__version__.py
easy_getch/easy_getch.py
easy_getch.egg-info/PKG-INFO
easy_getch.egg-info/SOURCES.txt
easy_getch.egg-info/dependency_links.txt
easy_getch.egg-info/top_level.txt
tests/__init__.py
tests/sanity_test.py