Metadata-Version: 2.1
Name: easy-getch
Version: 1.0.5
Summary: Easily get a single character
Home-page: https://github.com/cmccandless/easy-getch
Author: Corey McCandless
Author-email: crm1994@gmail.com
License: UNKNOWN
Platform: UNKNOWN
Classifier: Programming Language :: Python :: 3
Classifier: License :: OSI Approved :: MIT License
Classifier: Operating System :: OS Independent
